[
  {
    "shortName": "SII",
    "name": "IEEE/SICE International Symposium on System Integration",
    "start": "2025-01-21",
    "end": "2025-01-24",
    "deadline": "",
    "city": "Munich",
    "country": "Germany",
    "link": "",
    "type": "Conference",
    "addressLink": "",
    "note": ""
  },
  {
    "shortName": "HRI",
    "name": "International Conference on Human-Robot Interaction",
    "start": "2025-03-06",
    "end": "2025-03-06",
    "deadline": "2024-09-24",
    "city": "Melbourne",
    "country": "Australia",
    "link": "https://humanrobotinteraction.org/2025/",
    "type": "Conference",
    "addressLink": "https://maps.app.goo.gl/j2qT5KDk29f667rSA",
    "note": "We are excited to announce the 20th Annual ACM/IEEE International Conference on Human Robot Interaction (HRI). HRI is the annual conference for basic and applied HRI research, where researchers from across the world present their best work to exchange ideas about theory, technology, data, and science furthering the state-of-the-art in the field."
  },
  {
    "shortName": "ERF",
    "name": "European Robotics Forum",
    "start": "2025-03-25",
    "end": "2025-03-27",
    "deadline": "",
    "city": "Stuttgart",
    "country": "Germany",
    "link": "https://erf2025.eu/",
    "type": "Conference",
    "addressLink": "",
    "note": ""
  },
  {
    "shortName": "HRI",
    "name": "ACM/IEEE International Conference on Human-Robot Interaction",
    "start": "2025-03-03",
    "end": "2025-03-06",
    "deadline": "2024-10-01",
    "city": "South Wharf, VIC",
    "country": "Australia",
    "link": "https://humanrobotinteraction.org/2025/",
    "type": "Conference",
    "addressLink": "https://maps.app.goo.gl/CLHqNRCiybSaYFdDA",
    "note": ""
  },
  {
    "shortName": "ICMRACC",
    "name": "IEEE 1st International Conference on Materials, Robotics & Automation, Computer and Control",
    "start": "2025-03-14",
    "end": "2025-03-16",
    "deadline": "",
    "city": "Kannur",
    "country": "India",
    "link": "",
    "type": "Conference",
    "addressLink": "",
    "note": ""
  },
  {
    "shortName": "ICRA",
    "name": "IEEE International Conference on Robotics and Automation",
    "start": "2025-05-17",
    "end": "2025-05-23",
    "deadline": "",
    "city": "Atlanta",
    "country": "USA",
    "link": "",
    "type": "Conference",
    "addressLink": "",
    "note": ""
  },
  {
    "shortName": "CASE",
    "name": "IEEE International Conference on Automation Science and Engineering",
    "start": "2025-08-18",
    "end": "2025-08-22",
    "deadline": "",
    "city": "Anaheim, CA",
    "country": "USA",
    "link": "",
    "type": "Conference",
    "addressLink": "",
    "note": ""
  },
  {
    "shortName": "IROS",
    "name": "IEEE/RSJ International Conference on Intelligent Robots and Systems",
    "start": "2025-10-19",
    "end": "2025-10-25",
    "deadline": "",
    "city": "Hangzhou",
    "country": "China",
    "link": "",
    "type": "Conference",
    "addressLink": "",
    "note": ""
  }
]
