[
  {
    "name": "Latin American Summer School on Cognitive Robotics",
    "deadline": "",
    "city": "Santiago",
    "country": "Chile",
    "link": "https://lacoro.org/",
    "type": "School",
    "shortName": "LACORO",
    "start": "2023-01-03",
    "end": "2023-01-06",
    "addressLink": "https://goo.gl/maps/pZbpNurtMicUNs5m8",
    "note": ""
  },
  {
    "name": "EECI-IGS various summer schools",
    "deadline": "",
    "city": "various",
    "country": "",
    "link": "http://www.eeci-igsc.eu/doc/users/975/bib/2022-2023/eeciigsc2023programfinal.pdf",
    "type": "School",
    "shortName": "EECI-IGS",
    "start": "2023-02-01",
    "end": "2023-03-30",
    "addressLink": "",
    "note": ""
  },
  {
    "name": "DeepLearn Winter",
    "deadline": "",
    "city": "Bournemouth",
    "country": "UK",
    "link": "https://irdta.eu/deeplearn/2023wi/",
    "type": "School",
    "shortName": "DLWI",
    "start": "2023-01-17",
    "end": "2023-01-21",
    "addressLink": "",
    "note": ""
  },
  {
    "name": "EECI-IGS various summer schools",
    "deadline": "2023-03-19",
    "city": "various",
    "country": "",
    "link": "http://www.eeci-igsc.eu/doc/users/975/bib/2022-2023/eeciigsc2023programfinal.pdf",
    "type": "School",
    "shortName": "EECI-IGS",
    "start": "2023-04-01",
    "end": "2023-06-30",
    "addressLink": "",
    "note": ""
  },
  {
    "name": "Spring school on Mechanical aspects and applications of Haptics",
    "deadline": "",
    "city": "La Valletta",
    "country": "Malta",
    "link": "https://www.intuitive-itn.eu",
    "type": "School",
    "shortName": "INT",
    "start": "2023-04-17",
    "end": "2023-04-21",
    "addressLink": "",
    "note": ""
  },
  {
    "name": "IFToMM Italy International Summer School On Human-Centred Robotics.",
    "deadline": "2023-05-15",
    "city": "Ancona",
    "country": "Italy",
    "link": "https://human.univpm.it/human/",
    "type": "School",
    "shortName": "HCR",
    "start": "2023-06-26",
    "end": "2023-06-30",
    "addressLink": "",
    "note": ""
  },
  {
    "name": "Summer School on Multi-robot systems",
    "deadline": "",
    "city": "Prague",
    "country": "Czech Republic",
    "link": "http://mrs.felk.cvut.cz/summer-school-2023/",
    "type": "School",
    "shortName": "RASPRAGUE",
    "start": "2023-07-03",
    "end": "2023-07-07",
    "addressLink": "",
    "note": ""
  },
  {
    "name": "ETH Robotics Summer School",
    "deadline": "2023-03-24",
    "city": "Geneva",
    "country": "Switzerland",
    "link": "https://robotics-summerschool.ethz.ch/",
    "type": "School",
    "shortName": "ETHRSS",
    "start": "2023-07-09",
    "end": "2023-07-14",
    "addressLink": "",
    "note": ""
  },
  {
    "name": "Machine Learning Summer School",
    "deadline": "2023-05-15",
    "city": "Lisbon",
    "country": "Portugal",
    "link": "http://lxmls.it.pt/2023/",
    "type": "School",
    "shortName": "LML",
    "start": "2023-07-14",
    "end": "2023-07-20",
    "addressLink": "",
    "note": ""
  },
  {
    "name": "ELLIS Summer School on Probabilistic Machine Learning - Cambridge Unit",
    "deadline": "",
    "city": "Cambridge ",
    "country": "United Kingdom",
    "link": "https://ellis.eu/events/ellis-summer-school-on-probabilistic-machine-learning-cambridge-unit",
    "type": "School",
    "shortName": "ELLIS",
    "start": "2023-07-17",
    "end": "2023-07-21",
    "addressLink": "",
    "note": ""
  },
  {
    "name": "Mediterranean Machine Learning Summer School",
    "deadline": "2023-02-28",
    "city": "Thessaloniki",
    "country": "Greece",
    "link": "https://www.m2lschool.org/",
    "type": "School",
    "shortName": "MML",
    "start": "2023-08-28",
    "end": "2023-09-02",
    "addressLink": "",
    "note": ""
  },
  {
    "name": "Summer School on Singularities of Mechanisms and Robotic Manipulators",
    "deadline": "2023-07-31",
    "city": "Nantes",
    "country": "France",
    "link": "https://www.simero.org/index.php",
    "type": "School",
    "shortName": "SIMERO",
    "start": "2023-09-18",
    "end": "2023-09-22",
    "addressLink": "",
    "note": ""
  }
]
